dataspree/formconfig/__about__.c
dataspree/formconfig/__about__.cpython-313-x86_64-linux-gnu.so
dataspree/formconfig/__about__.py
dataspree/formconfig/__init__.py
dataspree/formconfig/core/__init__.py
dataspree/formconfig/core/exceptions.c
dataspree/formconfig/core/exceptions.cpython-313-x86_64-linux-gnu.so
dataspree/formconfig/core/exceptions.py
dataspree/formconfig/core/exceptions.pyi
dataspree/formconfig/core/naming.c
dataspree/formconfig/core/naming.cpython-313-x86_64-linux-gnu.so
dataspree/formconfig/core/naming.py
dataspree/formconfig/core/naming.pyi
dataspree/formconfig/data/__init__.py
dataspree/formconfig/data/base.c
dataspree/formconfig/data/base.cpython-313-x86_64-linux-gnu.so
dataspree/formconfig/data/base.py
dataspree/formconfig/data/base.pyi
dataspree/formconfig/data/base_configurable.c
dataspree/formconfig/data/base_configurable.cpython-313-x86_64-linux-gnu.so
dataspree/formconfig/data/base_configurable.py
dataspree/formconfig/data/base_configurable.pyi
dataspree/formconfig/data/config_data.c
dataspree/formconfig/data/config_data.cpython-313-x86_64-linux-gnu.so
dataspree/formconfig/data/config_data.py
dataspree/formconfig/data/config_data.pyi
dataspree/formconfig/data/config_enum.c
dataspree/formconfig/data/config_enum.cpython-313-x86_64-linux-gnu.so
dataspree/formconfig/data/config_enum.py
dataspree/formconfig/data/config_enum.pyi
dataspree/formconfig/data/config_list.c
dataspree/formconfig/data/config_list.cpython-313-x86_64-linux-gnu.so
dataspree/formconfig/data/config_list.py
dataspree/formconfig/data/config_list.pyi
dataspree/formconfig/data/config_optional.c
dataspree/formconfig/data/config_optional.cpython-313-x86_64-linux-gnu.so
dataspree/formconfig/data/config_optional.py
dataspree/formconfig/data/config_optional.pyi
dataspree/formconfig/data/config_union.c
dataspree/formconfig/data/config_union.cpython-313-x86_64-linux-gnu.so
dataspree/formconfig/data/config_union.py
dataspree_formconfig-0.1.0.dist-info/METADATA
dataspree_formconfig-0.1.0.dist-info/WHEEL
dataspree_formconfig-0.1.0.dist-info/RECORD
dataspree_formconfig-0.1.0.dist-info/licenses/LICENSE.txt
