Metadata-Version: 2.4
Name: dataspree-formconfig
Version: 0.1.0
Summary: Typed configuration models with form-based representations, defaults, and bidirectional parsing, supporting dynamic multi-step user input in form-driven UIs.
Project-URL: Homepage, https://www.data-spree.com/
Project-URL: Documentation, https://github.com/dataspree/dataspree_formconfig.git
Project-URL: Repository, https://github.com/dataspree/dataspree_formconfig.git
Author-email: Data Spree GmbH <info@data-spree.com>
License: Copyright (c) 2026 Data Spree GmbH - All Rights Reserved
License-File: LICENSE.txt
Keywords: dataspree,formconfig
Requires-Python: >=3.10
Requires-Dist: pydantic>=2.12.5
Requires-Dist: strenum>=0.4.15
Requires-Dist: typing-extensions>=4
